veem/__init__.py
veem/configuration.py
veem/constants.py
veem/exceptions.py
veem/client/__init__.py
veem/client/attachment.py
veem/client/authentication.py
veem/client/base.py
veem/client/contact.py
veem/client/customer.py
veem/client/exchange_rate.py
veem/client/invoice.py
veem/client/metadata.py
veem/client/payment.py
veem/client/veem.py
veem/client/webhook.py
veem/client/requests/__init__.py
veem/client/requests/account.py
veem/client/requests/address.py
veem/client/requests/amount.py
veem/client/requests/attachment.py
veem/client/requests/bank_account.py
veem/client/requests/contact.py
veem/client/requests/exchange_rate.py
veem/client/requests/invoice.py
veem/client/requests/payment.py
veem/client/requests/webhook.py
veem/client/responses/__init__.py
veem/client/responses/account.py
veem/client/responses/amount.py
veem/client/responses/attachment.py
veem/client/responses/exchange_rate.py
veem/client/responses/invoice.py
veem/client/responses/metadata.py
veem/client/responses/page.py
veem/client/responses/payment.py
veem/client/responses/payment_approval.py
veem/client/responses/push_payment_info.py
veem/client/responses/token.py
veem/client/responses/webhook.py
veem/models/__init__.py
veem/models/account.py
veem/models/account_list_parameters.py
veem/models/address.py
veem/models/amount.py
veem/models/approver.py
veem/models/attachment.py
veem/models/bank_account.py
veem/models/base.py
veem/models/batch.py
veem/models/batch_item.py
veem/models/contact.py
veem/models/contact_list_parameters.py
veem/models/context.py
veem/models/country_info.py
veem/models/exchange_rate.py
veem/models/invoice.py
veem/models/page.py
veem/models/payment.py
veem/models/payment_approval.py
veem/models/payment_list_parameters.py
veem/models/purpose_of_payment.py
veem/models/push_payment_info.py
veem/models/token_response.py
veem/models/veem_error_response.py
veem/models/webhook.py
veem/utils/__init__.py
veem/utils/rest.py
veem/utils/utilities.py
oveem-2.2.0.dist-info/LICENSE.md
oveem-2.2.0.dist-info/METADATA
oveem-2.2.0.dist-info/WHEEL
oveem-2.2.0.dist-info/namespace_packages.txt
oveem-2.2.0.dist-info/top_level.txt
oveem-2.2.0.dist-info/RECORD
