Metadata-Version: 2.1
Name: oveem
Version: 2.2.0
Summary: Veem Python SDK provides an interface to call Veem Global Payments APIs (https://www.veem.com).
Home-page: https://github.com/intelligenti/veem-python-sdk
Author: Intelligenti
Author-email: hello@intelligenti.io
License: UNKNOWN
Keywords: veem python intelligenti sdk b2b payment
Platform: UNKNOWN
Classifier: Development Status :: 5 - Production/Stable
Classifier: Environment :: Console
Classifier: Intended Audience :: Developers
Classifier: Intended Audience :: Financial and Insurance Industry
Classifier: License :: OSI Approved :: MIT License
Classifier: Operating System :: POSIX :: Linux
Classifier: Programming Language :: Python
Classifier: Programming Language :: Python :: 2
Classifier: Programming Language :: Python :: 2.7
Classifier: Programming Language :: Python :: 3
Classifier: Programming Language :: Python :: 3.4
Classifier: Topic :: Office/Business :: Financial
Classifier: Topic :: Software Development :: Libraries
Classifier: Topic :: Software Development :: Libraries :: Python Modules
Requires-Dist: attrdict
Requires-Dist: pyyaml
Requires-Dist: requests
Requires-Dist: six
Requires-Dist: urllib3
